LICENSE
MANIFEST.in
README.md
setup.py
moss/__init__.py
moss/buffers.py
moss/camera.py
moss/collision.py
moss/color.py
moss/context.py
moss/editor.py
moss/input.py
moss/loader.py
moss/logger.py
moss/material.py
moss/mesh.py
moss/mixer.py
moss/model.py
moss/physics.py
moss/project.py
moss/renderer.py
moss/shader.py
moss/texture.py
moss/transform.py
moss/window.py
moss/api/moss_api.py
moss/api/moss_api.rsxh
moss/res/DesertEagle_AO.png
moss/res/DesertEagle_C.png
moss/res/DesertEagle_M.png
moss/res/DesertEagle_N.png
moss/res/DesertEagle_R.png
moss/res/ak-12.mp3
moss/res/ak-12.mtl
moss/res/ak-12.obj
moss/res/camera.mtl
moss/res/camera.obj
moss/res/cube.obj
moss/res/deagle.mp3
moss/res/deagle.mtl
moss/res/deagle.obj
moss/res/icon.png
moss/res/icon_ico.ico
moss/res/icon_white.png
moss/res/logo.png
moss/res/monkey.obj
moss/res/plane.obj
moss/res/planks.png
moss/res/planksSpec.png
moss/res/sphere.mtl
moss/res/sphere.obj
moss/res/teapot.obj
moss/res/aluminum_scuffed/aluminum_scuffed_basecolor.png
moss/res/aluminum_scuffed/aluminum_scuffed_metallic.png
moss/res/aluminum_scuffed/aluminum_scuffed_normal.png
moss/res/aluminum_scuffed/aluminum_scuffed_roughness.png
moss/res/copper_scuffed/copper_scuffed_basecolor.png
moss/res/copper_scuffed/copper_scuffed_metallic.png
moss/res/copper_scuffed/copper_scuffed_normal.png
moss/res/copper_scuffed/copper_scuffed_roughness.png
moss/res/gold_scuffed/gold_scuffed_basecolor.png
moss/res/gold_scuffed/gold_scuffed_metallic.png
moss/res/gold_scuffed/gold_scuffed_normal.png
moss/res/gold_scuffed/gold_scuffed_roughness.png
moss/res/hdr_textures/foyer.hdr
moss/res/hdr_textures/square_night.hdr
moss/res/hdr_textures/train_station.hdr
moss/res/iron_scuffed/iron_scuffed_basecolor.png
moss/res/iron_scuffed/iron_scuffed_metallic.png
moss/res/iron_scuffed/iron_scuffed_normal.png
moss/res/iron_scuffed/iron_scuffed_roughness.png
moss/res/rusted_iron/rusted_iron_basecolor.png
moss/res/rusted_iron/rusted_iron_metallic.png
moss_engine.egg-info/PKG-INFO
moss_engine.egg-info/SOURCES.txt
moss_engine.egg-info/dependency_links.txt
moss_engine.egg-info/entry_points.txt
moss_engine.egg-info/requires.txt
moss_engine.egg-info/top_level.txt