Metadata-Version: 2.1
Name: moss-engine
Version: 0.0.3
Summary: A game engine written in Python using OpenGL.
Home-page: https://github.com/Aermoss/Moss
Author: Yusuf Rençber
Author-email: aermoss.0@gmail.com
License: MIT
License-File: LICENSE
